{
"english": [
 {
  "Staff Name": "Dr. Deepa Mary Francis",
  "Designation": "Asst. Professor(SG)",
  "Extn. No": 6158,
  "Email - ID": "deepa.f.mit@gmail.com"
 },
 {
  "Staff Name": "Dr. J. Lourdes Joavani",
  "Designation": "Asst. Professor",
  "Extn. No": 6436,
  "Email - ID": "joavani@gmail.com"
 },
 {
  "Staff Name": "Dr. A. R. S. Jayanth",
  "Designation": "Teaching Fellow",
  "Extn. No": 6444,
  "Email - ID": "sjay.r35@gmail.com"
 },
 {
  "Staff Name": null,
  "Designation": null,
  "Extn. No": null,
  "Email - ID": "ars_jayanth@mitindia.edu"
 },
 {
  "Staff Name": "Ms. I.Elisha",
  "Designation": "Teaching Fellow",
  "Extn. No": 6444,
  "Email - ID": " elizmartiz@gmail.com "
 },
 {
  "Staff Name": "Ms. P. Bharathi",
  "Designation": "Teaching Fellow",
  "Extn. No": 6438,
  "Email - ID": " baarti.sarathy@gmail.com"
 },
 {
  "Staff Name": "Ms. S. Maria Bridget Jenitta",
  "Designation": "Teaching Fellow",
  "Extn. No": 6438,
  "Email - ID": "mbjenny95@gmail.com "
 },
 {
  "Staff Name": "Ms.G.Preethi",
  "Designation": "Teaching Fellow",
  "Extn. No": 6438,
  "Email - ID": "gpreethi92@gmail.com"
 }
]
}